pyVoIP/RTP.py
pyVoIP/SIP.py
pyVoIP/__init__.py
pyVoIP/py.typed
pyVoIP/util.py
pyVoIP/VoIP/VoIP.py
pyVoIP/VoIP/__init__.py
pyVoIP/VoIP/status.py
pyVoIP-1.6.7.dist-info/LICENSE
pyVoIP-1.6.7.dist-info/METADATA
pyVoIP-1.6.7.dist-info/WHEEL
pyVoIP-1.6.7.dist-info/top_level.txt
pyVoIP-1.6.7.dist-info/RECORD
