Metadata-Version: 2.1
Name: pyVoIP
Version: 1.6.7
Summary: PyVoIP is a pure python VoIP/SIP/RTP library.
Home-page: https://github.com/tayler6000/pyVoIP
Author: Tayler Porter
Author-email: taylerporter@gmail.com
Project-URL: Bug Tracker, https://github.com/tayler6000/pyVoIP/issues
Project-URL: Documentaiton, https://pyvoip.readthedocs.io/
Classifier: Programming Language :: Python :: 3
Classifier: Operating System :: OS Independent
Classifier: Development Status :: 5 - Production/Stable
Classifier: Intended Audience :: Developers
Classifier: Intended Audience :: Telecommunications Industry
Classifier: Intended Audience :: Information Technology
Classifier: License :: OSI Approved :: GNU General Public License v3 (GPLv3)
Classifier: Natural Language :: English
Classifier: Topic :: Communications :: Internet Phone
Classifier: Topic :: Communications :: Telephony
Requires-Python: >=3.6
License-File: LICENSE
